streamlit_ace_cursor/__init__.py
streamlit_ace_cursor/version.py
streamlit_ace_cursor/frontend/build/00b386ead105b7b4e72dedc3c047802f.js
streamlit_ace_cursor/frontend/build/02ebbaff286dee0cee94caaf993701a5.js
streamlit_ace_cursor/frontend/build/03b6f5ed432b1096271448f530f79c3a.js
streamlit_ace_cursor/frontend/build/03cb1a484fcb851937e93afd75370352.js
streamlit_ace_cursor/frontend/build/0439a821b3d83aaee85404e6b2be5abd.js
streamlit_ace_cursor/frontend/build/051172af4df2228c8acf8d04d449ab1d.js
streamlit_ace_cursor/frontend/build/05ed365d25c7573321c0921893defcf2.js
streamlit_ace_cursor/frontend/build/05f2b6d27716f95c75421370d5ee9029.js
streamlit_ace_cursor/frontend/build/07011752aeaa58913a688453ba034167.js
streamlit_ace_cursor/frontend/build/0793cf610f32032db1d4c082bb541822.js
streamlit_ace_cursor/frontend/build/09b876087b43b5b3167eaa6dd8fa3260.js
streamlit_ace_cursor/frontend/build/09bd8cf88344af5acdf9a86f54a4cd04.js
streamlit_ace_cursor/frontend/build/0a4438ad4f6617ec42fb006d2c3da2ad.js
streamlit_ace_cursor/frontend/build/0a84849cb72c84fb6a9b4d831df64ffa.js
streamlit_ace_cursor/frontend/build/0a88e0d79e8ece225c2ffe37fb56fb83.js
streamlit_ace_cursor/frontend/build/0bbdfc82acc2ea66ba14ad4c65193773.js
streamlit_ace_cursor/frontend/build/0c14e3f2bbdb026c7dbdecf587f1df62.js
streamlit_ace_cursor/frontend/build/0c35d5ee6cc98b01f4e6380cd352c88b.js
streamlit_ace_cursor/frontend/build/0c93349d05810059db73cafb8956afd5.js
streamlit_ace_cursor/frontend/build/0d23aba2dc82c8a5b2c908efb76d1b53.js
streamlit_ace_cursor/frontend/build/0ffb18fb70c87335edee31a479f58a43.js
streamlit_ace_cursor/frontend/build/1046b30afca9b1942dd448bcafff2a95.js
streamlit_ace_cursor/frontend/build/10e05485016a6745406904ce95e92c0d.js
streamlit_ace_cursor/frontend/build/12233d9585e93082494c21942241a9c0.js
streamlit_ace_cursor/frontend/build/1261ef2b1ed112b8f15686ce9b968b0f.js
streamlit_ace_cursor/frontend/build/144e38358d6dddaaa6bc2602bf312b6a.js
streamlit_ace_cursor-0.1.2.dist-info/LICENSE
streamlit_ace_cursor-0.1.2.dist-info/METADATA
streamlit_ace_cursor-0.1.2.dist-info/WHEEL
streamlit_ace_cursor-0.1.2.dist-info/top_level.txt
streamlit_ace_cursor-0.1.2.dist-info/RECORD
