Metadata-Version: 2.1
Name: streamlit_ace_cursor
Version: 0.1.2
Summary: Ace editor component for Streamlit.
Home-page: https://share.streamlit.io/okld/streamlit-gallery/main?p=ace-editor
Author: okld
License: MIT
Requires-Python: >=3.6
License-File: LICENSE
Requires-Dist: streamlit >=0.63
